Metadata-Version: 1.0
Name: ciscoconfbot
Version: 1.0.14
Summary: Webex Teams bot for configuring Cisco devices
Home-page: UNKNOWN
Author: naonder
Author-email: nate.a.onder@gmail.com
License: MIT
Platform: UNKNOWN
